Metadata-Version: 2.1
Name: galaxie-docs
Version: 0.5.2
Summary: Galaxie Docs is a low-tech survival ToolKit for documents conversion
Author: Tuuux
Project-URL: Homepage, https://gitlab.com/Tuuux/galaxie-docs
Project-URL: Issues, https://gitlab.com/Tuuux/galaxie-docs/-/issues
Project-URL: Readthedocs, http://galaxie-docs.readthedocs.io
Keywords: Galaxie,docs,yaml,markdown
Classifier: Environment :: Console
Classifier: Intended Audience :: Developers
Classifier: License :: Public Domain
Classifier: Topic :: Software Development :: Libraries :: Python Modules
Classifier: Programming Language :: Python
Classifier: Programming Language :: Python :: 3 :: Only
Requires-Python: >=3.0
License-File: LICENSE
Requires-Dist: wheel
Requires-Dist: markdown
Requires-Dist: Pygments
Provides-Extra: tests
Requires-Dist: coverage; extra == "tests"
Requires-Dist: wheel; extra == "tests"
Requires-Dist: markdown; extra == "tests"
Requires-Dist: Pygments; extra == "tests"
Requires-Dist: mock<4,>=1.0.1; python_version < "3.4" and extra == "tests"
